setup.py
both_probability/Binomialdistribution.py
both_probability/Gaussiandistribution.py
both_probability/Generaldistribution.py
both_probability/__init__.py
both_probability.egg-info/PKG-INFO
both_probability.egg-info/SOURCES.txt
both_probability.egg-info/dependency_links.txt
both_probability.egg-info/not-zip-safe
both_probability.egg-info/top_level.txt