Metadata-Version: 1.0
Name: both-probability
Version: 1.1
Summary: Gaussian and Binomial distributions
Home-page: UNKNOWN
Author: Ishita Arora
Author-email: ishita.arora28@gmail.com
License: UNKNOWN
Platform: UNKNOWN
